llamazure/tools/__init__.py
llamazure/tools/migrate/__init__.py
llamazure/tools/migrate/__main__.py
llamazure/tools/migrate/dashboard.py
llamazure/tools/migrate/util.py
llamazure/tools/migrate/workbook.py
llamazure/tools/migrate/applicationinsights/r/m/insights/workbooks.py
llamazure/tools/migrate/c/r/v1/types.py
llamazure/tools/migrate/c/r/v3/managedidentity.py
llamazure/tools/migrate/c/r/v5/types.py
llamazure/tools/migrate/portal/r/m/portal/portal.py
llamazure.tools-0.2.1.dist-info/METADATA
llamazure.tools-0.2.1.dist-info/WHEEL
llamazure.tools-0.2.1.dist-info/entry_points.txt
llamazure.tools-0.2.1.dist-info/namespace_packages.txt
llamazure.tools-0.2.1.dist-info/top_level.txt
llamazure.tools-0.2.1.dist-info/RECORD
