Metadata-Version: 2.1
Name: llamazure.tools
Version: 0.2.1
Summary: A bundle of helpful tools for dealing with Azure
Author: Daniel Goldman
License: Round Robin 2.0.0
Classifier: Development Status :: 3 - Alpha
Classifier: Programming Language :: Python :: 3.9
Classifier: Programming Language :: Python :: 3.10
Classifier: Programming Language :: Python :: 3.11
Classifier: Programming Language :: Python :: 3.12
Classifier: Programming Language :: Python :: 3.13
Classifier: Topic :: Utilities
Requires-Python: >=3.10
Requires-Dist: azure-identity<2.0.0,>=1.4.0
Requires-Dist: click~=8.0
Requires-Dist: llamazure.azrest~=0.4.0
Requires-Dist: llamazure.rid~=0.1.0
